zhunter/CheckBoxListWidget.py
zhunter/__init__.py
zhunter/colors.py
zhunter/gui.py
zhunter/io.py
zhunter/key_binding.py
zhunter/line_list_selection.py
zhunter/misc.py
zhunter/spectral_functions.py
zhunter/spectroscopic_system.py
zhunter/velocity_plot.py
zhunter/data/lines/basic_line_list.csv
zhunter/data/lines/basic_line_list.ecsv
zhunter/data/lines/emission_lines.csv
zhunter/data/lines/emission_lines.ecsv
zhunter/data/lines/fine_structure.csv
zhunter/data/lines/fine_structure.ecsv
zhunter/data/lines/line_ratio.csv
zhunter/data/sky_background/sky_background_norm_opt_to_nir.ecsv.gz
zhunter/data/tellurics/mk_trans_zm_50_20.dat.gz
zhunter/data/tellurics/sky_transimission_opt_to_nir.ecsv.gz
zhunter/data/tellurics/synth_tellurics_350_1100nm.csv.gz
zhunter/ui/key_bindings.ui
zhunter/ui/line_list_selection_dialog.ui
zhunter/ui/main_frame.ui
zhunter/ui/velocity_plot.ui
zhunter-0.10.3.dist-info/LICENSE
zhunter-0.10.3.dist-info/METADATA
zhunter-0.10.3.dist-info/WHEEL
zhunter-0.10.3.dist-info/entry_points.txt
zhunter-0.10.3.dist-info/top_level.txt
zhunter-0.10.3.dist-info/RECORD
