Metadata-Version: 2.1
Name: zhunter
Version: 0.10.3
Summary: A Python-based visualization tool for finding redshifts and manipulating astronomical spectra.
Home-page: https://github.com/JPalmerio/zHunter
Author: Jesse Palmerio
Author-email: jesse.palmerio@obspm.fr
Project-URL: Bug Tracker, https://github.com/JPalmerio/zHunter/issues
Classifier: Programming Language :: Python :: 3.9
Classifier: License :: OSI Approved :: GNU General Public License v3 (GPLv3)
Classifier: Operating System :: OS Independent
Classifier: Natural Language :: English
Classifier: Intended Audience :: Science/Research
Classifier: Topic :: Scientific/Engineering :: Astronomy
Classifier: Topic :: Scientific/Engineering :: Visualization
Classifier: Development Status :: 4 - Beta
Requires-Python: >=3.9
License-File: LICENSE
Requires-Dist: pyqt6 (>=6.4)
Requires-Dist: pyqtgraph (>=0.13.1)
Requires-Dist: numpy (>=1.24)
Requires-Dist: astropy (>=5.2)
Requires-Dist: matplotlib (>=3.6)
Requires-Dist: pandas (>=1.5)
Requires-Dist: spectres (>=2.2)
Requires-Dist: specutils (>=1.9)
